pycubool/__init__.py
pycubool/bridge.py
pycubool/gviz.py
pycubool/io.py
pycubool/libcubool.so
pycubool/matrix.py
pycubool/utils.py
pycubool/vector.py
pycubool/wrapper.py
pycubool-1.2.0.dist-info/LICENSE
pycubool-1.2.0.dist-info/METADATA
pycubool-1.2.0.dist-info/WHEEL
pycubool-1.2.0.dist-info/top_level.txt
pycubool-1.2.0.dist-info/RECORD
