Metadata-Version: 2.1
Name: pycubool
Version: 1.2.0
Summary: cuBool library python bindings
Home-page: https://github.com/JetBrains-Research/cuBool
Author: Egor Orachyov
Author-email: egororachyov@gmail.com
License: MIT
Project-URL: cuBool project, https://github.com/JetBrains-Research/cuBool
Project-URL: Bug Tracker, https://github.com/JetBrains-Research/cuBool/issues
Keywords: python,cplusplus,sparse-matrix,linear-algebra,graph-analysis,graph-algorithms,graphblas,nvidia-cuda
Platform: UNKNOWN
Classifier: Development Status :: 5 - Production/Stable
Classifier: Programming Language :: Python :: 3
Classifier: Programming Language :: C++
Classifier: License :: OSI Approved :: MIT License
Classifier: Operating System :: POSIX :: Linux
Classifier: Environment :: GPU :: NVIDIA CUDA
Classifier: Environment :: Console
Classifier: Intended Audience :: Developers
Classifier: Intended Audience :: End Users/Desktop
Classifier: Intended Audience :: Information Technology
Classifier: Intended Audience :: Science/Research
Classifier: Natural Language :: English
Classifier: Topic :: Scientific/Engineering :: Information Analysis
Requires-Python: >=3.0
